odbg/__init__.py
odbg/batch_submission.py
odbg/download_results.py
odbg-0.1.0.dist-info/METADATA
odbg-0.1.0.dist-info/WHEEL
odbg-0.1.0.dist-info/RECORD
