Metadata-Version: 2.1
Name: odbg
Version: 0.1.0
Summary: Open Data Badger
Author: Ashim Mahara
Author-email: ashim@shivatech.dev
Requires-Python: >=3.12,<4.0
Classifier: Programming Language :: Python :: 3
Classifier: Programming Language :: Python :: 3.12
Requires-Dist: fastparquet (>=2024.5.0,<2025.0.0)
Requires-Dist: openai (>=1.35.6,<2.0.0)
Requires-Dist: pandas (>=2.2.2,<3.0.0)
Requires-Dist: pyarrow (>=16.1.0,<17.0.0)
Requires-Dist: tabulate (>=0.9.0,<0.10.0)
Requires-Dist: tiktoken (>=0.7.0,<0.8.0)
Requires-Dist: tqdm (>=4.66.4,<5.0.0)
